README.md
setup.py
nextplus/__init__.py
nextplus/client.py
nextplus/table.py
nextplus/tables.py
nextplus.egg-info/PKG-INFO
nextplus.egg-info/SOURCES.txt
nextplus.egg-info/dependency_links.txt
nextplus.egg-info/not-zip-safe
nextplus.egg-info/requires.txt
nextplus.egg-info/top_level.txt
tests/__init__.py
tests/test_client.py